Stackinator-4.0.data/scripts/stack-config
stackinator/__init__.py
stackinator/builder.py
stackinator/cache.py
stackinator/main.py
stackinator/recipe.py
stackinator/schema.py
stackinator/spack_util.py
stackinator/etc/Make.inc
stackinator/etc/add-compiler-links.py
stackinator/etc/bwrap-mutable-root.sh
stackinator/schema/cache.json
stackinator/schema/compilers.json
stackinator/schema/config.json
stackinator/schema/environments.json
stackinator/templates/Make.user
stackinator/templates/Makefile
stackinator/templates/Makefile.compilers
stackinator/templates/Makefile.environments
stackinator/templates/Makefile.generate-config
stackinator/templates/compilers.bootstrap.spack.yaml
stackinator/templates/compilers.gcc.spack.yaml
stackinator/templates/compilers.llvm.spack.yaml
stackinator/templates/environments.spack.yaml
stackinator/templates/repos.yaml
stackinator/templates/stack-debug.sh
Stackinator-4.0.dist-info/LICENSE
Stackinator-4.0.dist-info/METADATA
Stackinator-4.0.dist-info/WHEEL
Stackinator-4.0.dist-info/top_level.txt
Stackinator-4.0.dist-info/RECORD
