Metadata-Version: 2.1
Name: Stackinator
Version: 4.0
Summary: Stackinator is a tool for building a scientific software stack from a recipe for vClusters on CSCS' Alps infrastructure
Home-page: https://github.com/eth-cscs/stackinator
Author: Swiss National Supercomputing Center (CSCS/ETH Zurich)
License: BSD 3-Clause
Platform: UNKNOWN
Classifier: Development Status :: 5 - Production/Stable
Classifier: Programming Language :: Python :: 3.6
Classifier: Programming Language :: Python :: 3.7
Classifier: Programming Language :: Python :: 3.8
Classifier: Programming Language :: Python :: 3.9
Classifier: Programming Language :: Python :: 3.10
Classifier: Programming Language :: Python :: 3.11
Classifier: License :: OSI Approved :: BSD License
Classifier: Operating System :: POSIX :: Linux
Classifier: Environment :: Console
Requires-Python: >=3.6
License-File: LICENSE
Requires-Dist: Jinja2
Requires-Dist: jsonschema
Requires-Dist: PyYAML
